Metadata-Version: 1.0
Name: circlecli
Version: 1.3.0
Summary: Unofficial CircleCI CLI tool
Home-page: https://github.com/TheRealJoeLinux/circlecli
Author: Joey Espinosa
Author-email: jlouis.espinosa@gmail.com
License: MIT License
Keywords: circleci,cicd,rest,api,cli,command,command-line
Platform: UNKNOWN
